pyfault.py
_vendor/README.md
_vendor/__init__.py
_vendor/tblib/__init__.py
_vendor/tblib/decorators.py
_vendor/tblib/pickling_support.py
_vendor/tblib-3.1.0.dist-info/licenses/AUTHORS.rst
_vendor/tblib-3.1.0.dist-info/licenses/LICENSE
pyfault-0.1.5.dist-info/licenses/LICENSE.txt
_vendor/tblib-3.1.0.dist-info/INSTALLER
_vendor/tblib-3.1.0.dist-info/METADATA
_vendor/tblib-3.1.0.dist-info/RECORD
_vendor/tblib-3.1.0.dist-info/REQUESTED
_vendor/tblib-3.1.0.dist-info/WHEEL
_vendor/tblib-3.1.0.dist-info/top_level.txt
pyfault-0.1.5.dist-info/METADATA
pyfault-0.1.5.dist-info/WHEEL
pyfault-0.1.5.dist-info/top_level.txt
pyfault-0.1.5.dist-info/RECORD
