Metadata-Version: 2.4
Name: pyfault
Version: 0.1.5
Summary: Memfault Python exception handler
Requires-Python: >=3.9
License-File: LICENSE.txt
Requires-Dist: requests>=2.32.4
Dynamic: license-file
